pyvww/__init__.py
pyvww/pytorch/__init__.py
pyvww/pytorch/datasets.py
pyvww/utils/__init__.py
pyvww/utils/visualwakewords.py
pyvww-0.1.1.dist-info/LICENSE
pyvww-0.1.1.dist-info/METADATA
pyvww-0.1.1.dist-info/WHEEL
pyvww-0.1.1.dist-info/top_level.txt
pyvww-0.1.1.dist-info/RECORD
