Metadata-Version: 2.1
Name: pyvww
Version: 0.1.1
Summary: Python API to work with the Visual Wake Words Dataset.
Home-page: https://github.com/Mxbonn/visualwakewords
Author: Maxim Bonnaerens
Author-email: maxim@bonnaerens.be
License: Apache 2.0
Platform: UNKNOWN
Requires-Dist: pycocotools
Requires-Dist: torchvision
